tokenvault_sdk/__init__.py
tokenvault_sdk/config.py
tokenvault_sdk/exceptions.py
tokenvault_sdk/logging_config.py
tokenvault_sdk/tracker.py
tokenvault_sdk-1.0.2.dist-info/METADATA
tokenvault_sdk-1.0.2.dist-info/WHEEL
tokenvault_sdk-1.0.2.dist-info/top_level.txt
tokenvault_sdk-1.0.2.dist-info/RECORD
