Metadata-Version: 2.4
Name: tokenvault-sdk
Version: 1.0.2
Summary: Python SDK for AI agents to track LLM usage and forward billing data to TokenVault
Author: TokenVault Team
License: MIT
Project-URL: Homepage, https://github.com/tokenvault/tokenvault-sdk
Project-URL: Documentation, https://docs.tokenvault.io/sdk
Project-URL: Repository, https://github.com/tokenvault/tokenvault-sdk
Project-URL: Issues, https://github.com/tokenvault/tokenvault-sdk/issues
Keywords: llm,usage-tracking,billing,ai-agents,groq
Classifier: Development Status :: 3 - Alpha
Classifier: Intended Audience :: Developers
Classifier: License :: OSI Approved :: MIT License
Classifier: Programming Language :: Python :: 3
Classifier: Programming Language :: Python :: 3.11
Classifier: Programming Language :: Python :: 3.12
Classifier: Topic :: Software Development :: Libraries :: Python Modules
Requires-Python: >=3.11
Requires-Dist: redis>=5.0.0
Requires-Dist: httpx>=0.25.0
Requires-Dist: tenacity>=8.2.0
Requires-Dist: groq>=0.4.0
Provides-Extra: dev
Requires-Dist: pytest>=7.4.0; extra == "dev"
Requires-Dist: pytest-asyncio>=0.21.0; extra == "dev"
Requires-Dist: hypothesis>=6.92.0; extra == "dev"
Requires-Dist: pytest-cov>=4.1.0; extra == "dev"
Requires-Dist: pytest-mock>=3.12.0; extra == "dev"
